sionna_vispy/__init__.py
sionna_vispy/__version__.py
sionna_vispy/previewer.py
sionna_vispy-1.1.0.dist-info/METADATA
sionna_vispy-1.1.0.dist-info/WHEEL
sionna_vispy-1.1.0.dist-info/licenses/LICENSE.md
sionna_vispy-1.1.0.dist-info/RECORD
