Metadata-Version: 2.4
Name: sionna-vispy
Version: 1.1.0
Summary: VisPy scene previewer for Sionna
Project-URL: Changelog, https://github.com/jeertmans/sionna-vispy/releases
Project-URL: Documentation, https://github.com/jeertmans/sionna-vispy
Project-URL: Founding, https://github.com/sponsors/jeertmans
Project-URL: Homepage, https://github.com/jeertmans/sionna-vispy
Project-URL: Repository, https://github.com/jeertmans/sionna-vispy
Author-email: Jérome Eertmans <jeertmans@icloud.com>
License-Expression: MIT
License-File: LICENSE.md
Keywords: preview,raytracing,sionna,vispy
Classifier: License :: OSI Approved :: MIT License
Classifier: Operating System :: OS Independent
Classifier: Programming Language :: Python :: 3
Classifier: Programming Language :: Python :: 3.8
Classifier: Programming Language :: Python :: 3.9
Classifier: Programming Language :: Python :: 3.10
Classifier: Programming Language :: Python :: 3.11
Classifier: Programming Language :: Python :: 3.12
Classifier: Topic :: Multimedia :: Graphics
Classifier: Topic :: Scientific/Engineering
Requires-Python: >=3.8
Requires-Dist: drjit>=1.0.3
Requires-Dist: matplotlib>=3.7.5
Requires-Dist: mitsuba>=3.6.2
Requires-Dist: numpy>=1.24.4
Requires-Dist: sionna-rt>=1.1.0
Requires-Dist: vispy>=0.14.2
Provides-Extra: recommended
Requires-Dist: jupyter-rfb>=0.3.3; extra == 'recommended'
Requires-Dist: pyside6>=6.0.0; extra == 'recommended'
